Workbook

Sheet overview_2025-04-11
A1: test_file | B1: nr_utterances | C1: analyzer | D1: triple_precision | E1: precision triple elements | F1: subjects_precision | G1: objects_precision | H1: predicates_precision | I1: perspectives_precision | J1: certainty_precision | K1: polarity_precision | L1: sentiment_precision
A2: answer_ellipsis | B2: 101 | C2: convBERT | D2: 0.99009901 | E2: 21.782178 | F2: 52.475248 | G2: 5.9405941 | H2: 6.9306931 | I2: 66.666667 | J2: 100 | K2: 100 | L2: 0
C3: Qwen2.5 | D3: 2.970297 | E3: 26.40264 | F3: 60.39604 | G3: 8.9108911 | H3: 9.9009901 | I3: 68 | J3: 97 | K3: 90 | L3: 17
A4: coordination | B4: 82 | C4: convBERT | D4: 6.097561 | E4: 32.926829 | F4: 58.536585 | G4: 21.95122 | H4: 18.292683 | I4: 66.666667 | J4: 100 | K4: 100 | L4: 0
C5: Qwen2.5 | D5: 2.4390244 | E5: 31.707317 | F5: 63.414634 | G5: 8.5365854 | H5: 23.170732 | I5: 70.042194 | J5: 100 | K5: 91.139241 | L5: 18.987342
A6: coreference | B6: 78 | C6: convBERT | D6: 1.2820513 | E6: 17.094017 | F6: 26.923077 | G6: 20.512821 | H6: 3.8461538 | I6: 66.666667 | J6: 100 | K6: 100 | L6: 0
C7: Qwen2.5 | D7: 0 | E7: 14.957265 | F7: 28.205128 | G7: 10.25641 | H7: 6.4102564 | I7: 67.982456 | J7: 98.684211 | K7: 89.473684 | L7: 15.789474
A8: declarative_statements | B8: 91 | C8: convBERT | D8: 1.0989011 | E8: 28.205128 | F8: 58.241758 | G8: 18.681319 | H8: 7.6923077 | I8: 66.26506 | J8: 100 | K8: 98.795181 | L8: 0
C9: Qwen2.5 | D9: 1.0989011 | E9: 25.641026 | F9: 58.241758 | G9: 8.7912088 | H9: 9.8901099 | I9: 67.399267 | J9: 96.703297 | K9: 94.505495 | L9: 10.989011
A10: declarative_statements_negated | B10: 79 | C10: convBERT | D10: 1.2658228 | E10: 27.848101 | F10: 54.43038 | G10: 20.253165 | H10: 8.8607595 | I10: 65.217391 | J10: 100 | K10: 95.652174 | L10: 0
C11: Qwen2.5 | D11: 2.5316456 | E11: 24.472574 | F11: 55.696203 | G11: 8.8607595 | H11: 8.8607595 | I11: 56.410256 | J11: 94.871795 | K11: 62.820513 | L11: 11.538462
A12: explicit_no_answers | B12: 47 | C12: convBERT | D12: 2.1276596 | E12: 23.404255 | F12: 51.06383 | G12: 8.5106383 | H12: 10.638298 | I12: 65.789474 | J12: 100 | K12: 97.368421 | L12: 0
C13: Qwen2.5 | D13: 4.2553191 | E13: 27.659574 | F13: 59.574468 | G13: 8.5106383 | H13: 14.893617 | I13: 61.702128 | J13: 97.87234 | K13: 72.340426 | L13: 14.893617
A14: explicit_yes_answers | B14: 59 | C14: convBERT | D14: 1.6949153 | E14: 23.728814 | F14: 54.237288 | G14: 5.0847458 | H14: 11.864407 | I14: 66.666667 | J14: 100 | K14: 100 | L14: 0
C15: Qwen2.5 | D15: 0 | E15: 24.293785 | F15: 62.711864 | G15: 1.6949153 | H15: 8.4745763 | I15: 66.081871 | J15: 94.736842 | K15: 96.491228 | L15: 7.0175439

Sheet Errors Qwen2.5
B1: empty | C1: normalization | D1: different | E1: related | F1: posessive | H1: normalization | I1: different | J1: related | K1: complement | L1: aux | M1: negattion | O1: normalization | P1: different | Q1: related | R1: posessive | S1: coref
A2: Mismatch in triple object: != dance | B2: 1 | G2: Mismatch in triple predicate: ask-about != are from | I2: 1 | N2: Mismatch in triple subject: alphabet != speaker1 | P2: 1
A3: Mismatch in triple object: != hunt | B3: 1 | G3: Mismatch in triple predicate: be != are in | L3: 1 | N3: Mismatch in triple subject: attraction != that | P3: 1
A4: Mismatch in triple object: != in nyc | B4: 1 | G4: Mismatch in triple predicate: be != are up to | L4: 1 | N4: Mismatch in triple subject: dahua's-market != speaker1 's store | Q4: 1
A5: Mismatch in triple object: != lots of stuff | B5: 1 | G5: Mismatch in triple predicate: be != making | I5: 1 | N5: Mismatch in triple subject: deon != speaker1 | P5: 1
A6: Mismatch in triple object: != outdoors | B6: 1 | G6: Mismatch in triple predicate: be != studying | I6: 1 | N6: Mismatch in triple subject: everything != speaker1 | P6: 1
A7: Mismatch in triple object: != pink | B7: 1 | G7: Mismatch in triple predicate: be != work at | I7: 1 | N7: Mismatch in triple subject: fare != the fare | O7: 1
A8: Mismatch in triple object: - != indian mountains | D8: 1 | G8: Mismatch in triple predicate: be-a != are in | L8: 1 | N8: Mismatch in triple subject: fitting-room != the fitting room | O8: 1
A9: Mismatch in triple object: 14-yuan != 14 yuan | C9: 1 | G9: Mismatch in triple predicate: be-a != do | I9: 1 | N9: Mismatch in triple subject: google != speaker1 | P9: 1
A10: Mismatch in triple object: 1500 != thanksgiving | D10: 1 | G10: Mismatch in triple predicate: be-around != is around | H10: 1 | N10: Mismatch in triple subject: grandma != speaker1 | P10: 1
A11: Mismatch in triple object: 2500-yuan-per-month != 2500 yuan a month | C11: 1 | G11: Mismatch in triple predicate: be-babysitter != do | I11: 1 | N11: Mismatch in triple subject: internet != speaker1 | P11: 1
A12: Mismatch in triple object: 3000-rib-per-month != 3000 rib per month | C12: 1 | G12: Mismatch in triple predicate: be-enlisted-in != enlisted in | H12: 1 | N12: Mismatch in triple subject: it != speaker1 's favorite color | P12: 1
A13: Mismatch in triple object: 35-years-old-unmarried != high school japanese | D13: 1 | G13: Mismatch in triple predicate: be-fairly-big != is | L13: 1 | N13: Mismatch in triple subject: melbourne-zoo != that | P13: 1
A14: Mismatch in triple object: 5-years != it field | D14: 1 | G14: Mismatch in triple predicate: be-favorite-movie != is | L14: 1 | N14: Mismatch in triple subject: music != speaker1 | P14: 1
A15: Mismatch in triple object: 88267894-extension-to-208 != 88267894 extension to 208 | C15: 1 | G15: Mismatch in triple predicate: be-from != are from | H15: 1 | N15: Mismatch in triple subject: people != speaker1 | P15: 1
A16: Mismatch in triple object: alex != jazz | D16: 1 | G16: Mismatch in triple predicate: be-from != is | L16: 1 | N16: Mismatch in triple subject: pug != speaker1 | P16: 1
A17: Mismatch in triple object: alone-time != indian mountains | D17: 1 | G17: Mismatch in triple predicate: be-from != move to america from | I17: 1 | N17: Mismatch in triple subject: radio-station != speaker1 | P17: 1
A18: Mismatch in triple object: alphabet != the alphabet | C18: 1 | G18: Mismatch in triple predicate: be-from != visit | I18: 1 | N18: Mismatch in triple subject: slackers != speaker1 's favorite movie | P18: 1
A19: Mismatch in triple object: apple != dolls | D19: 1 | G19: Mismatch in triple predicate: be-great != like to | I19: 1 | N19: Mismatch in triple subject: someday != speaker1 | P19: 1
A20: Mismatch in triple object: aspire-to-be-like != listen to rap | D20: 1 | G20: Mismatch in triple predicate: be-heck-of-a != do | I20: 1 | N20: Mismatch in triple subject: speaker1 != guangzhou | P20: 1
A21: Mismatch in triple object: attraction != melbourne zoo | D21: 1 | G21: Mismatch in triple predicate: be-in != is | L21: 1 | N21: Mismatch in triple subject: speaker1 != playing d&d | P21: 1
A22: Mismatch in triple object: baked-ziti != baked ziti | C22: 1 | G22: Mismatch in triple predicate: be-lawyer != do | I22: 1 | N22: Mismatch in triple subject: speaker1 != speaker1 's biggest fear | R22: 1
A23: Mismatch in triple object: band != heavy metal | E23: 1 | G23: Mismatch in triple predicate: be-loyal != like to do for | I23: 1 | N23: Mismatch in triple subject: speaker1 != speaker1 's favorite color | R23: 1
A24: Mismatch in triple object: bike != look at the alphabet | D24: 1 | G24: Mismatch in triple predicate: be-name != like | I24: 1 | N24: Mismatch in triple subject: speaker1 != speaker1 's favorite disney character | R24: 1
A25: Mismatch in triple object: birds != thanksgiving | D25: 1 | G25: Mismatch in triple predicate: be-name-of != do for | I25: 1 | N25: Mismatch in triple subject: speaker1 != speaker1 's favorite food | R25: 1
A26: Mismatch in triple object: blonde != pink | D26: 1 | G26: Mismatch in triple predicate: be-next-to != is located | J26: 1 | N26: Mismatch in triple subject: speaker1 != speaker1 's favorite holiday | R26: 1
A27: Mismatch in triple object: books != look at the alphabet | D27: 1 | G27: Mismatch in triple predicate: be-on != ride | I27: 1 | N27: Mismatch in triple subject: speaker1 != speaker1 's favorite homemade meal | R27: 1
A28: Mismatch in triple object: brown != mickey mouse | D28: 1 | G28: Mismatch in triple predicate: be-on-the-other-side-of != enlisted in | I28: 1 | N28: Mismatch in triple subject: speaker1 != speaker1 's favorite movie | R28: 1
A29: Mismatch in triple object: call-of-duty != dolls | D29: 1 | G29: Mismatch in triple predicate: be-rude != live | I29: 1 | N29: Mismatch in triple subject: speaker1 != speaker1 's favorite team | R29: 1
A30: Mismatch in triple object: canadian-army != the canadian army | C30: 1 | G30: Mismatch in triple predicate: be-sick != do for fun | I30: 1 | N30: Mismatch in triple subject: speaker1 != speaker1 's favorite thing | R30: 1
A31: Mismatch in triple object: cane != country music | D31: 1 | G31: Mismatch in triple predicate: be-vegetarian != are from | I31: 1 | N31: Mismatch in triple subject: speaker1 != speaker1 's major | R31: 1
A32: Mismatch in triple object: cat-mouse-dog-biscuit != one dog sugar | D32: 1 | G32: Mismatch in triple predicate: be-worried-about != is | L32: 1 | N32: Mismatch in triple subject: speaker1 != speaker1 's plans | R32: 1
A33: Mismatch in triple object: cats-vanilla-ice-cream != collect hats | D33: 1 | G33: Mismatch in triple predicate: collect != do for fun | I33: 1 | N33: Mismatch in triple subject: speaker1 != speaker2 's favorite movie | R33: 1
A34: Mismatch in triple object: classes-for-drawing != high school japanese | D34: 1 | G34: Mismatch in triple predicate: could-teach != like to | I34: 1 | N34: Mismatch in triple subject: speaker1 != speaker2 's favorite pizza toppings | R34: 1
A35: Mismatch in triple object: classic-high-heels != black | D35: 1 | G35: Mismatch in triple predicate: do != enlisted in | I35: 1 | N35: Mismatch in triple subject: speaker1 != speaker2 's hobbies | R35: 1
A36: Mismatch in triple object: clean != miami | D36: 1 | G36: Mismatch in triple predicate: do != is | I36: 1 | N36: Mismatch in triple subject: speaker1 != that show | P36: 1
A37: Mismatch in triple object: collecting-baking-stuffs != baking stuffs | C37: 1 | G37: Mismatch in triple predicate: do-for-fun != collecting | I37: 1 | N37: Mismatch in triple subject: speaker1 != the starting salary | P37: 1
A38: Mismatch in triple object: college-of-alabama != geology | D38: 1 | G38: Mismatch in triple predicate: do-for-fun != do for fun | H38: 1 | N38: Mismatch in triple subject: speaker1 != the telephone number | P38: 1
A39: Mismatch in triple object: colts != the colts | C39: 1 | G39: Mismatch in triple predicate: do-not-play != play | I39: 1 | N39: Mismatch in triple subject: speaker2 != speaker1 's favorite team | R39: 1
A40: Mismatch in triple object: computer != country music | D40: 1 | G40: Mismatch in triple predicate: donate-to != is | I40: 1 | N40: Mismatch in triple subject: speaker2 != speaker2 's hobbies | R40: 1
A41: Mismatch in triple object: condo != in nyc | D41: 1 | G41: Mismatch in triple predicate: drink != have in the back | J41: 1 | L41: 1 | N41: Mismatch in triple subject: telephone-number != the telephone number | O41: 1
A42: Mismatch in triple object: cook-good-meals != baked ziti | D42: 1 | G42: Mismatch in triple predicate: enjoy-doing != enjoy | H42: 1 | N42: Mismatch in triple subject: thing != speaker1 | P42: 1
A43: Mismatch in triple object: cool != play music | D43: 1 | G43: Mismatch in triple predicate: expect != going to | L43: 1 | N43: Mismatch in triple subject: wife-of-speaker1 != speaker2 | R43: 1
A44: Mismatch in triple object: corner != the corner | C44: 1 | G44: Mismatch in triple predicate: explore != exploring | L44: 1 | O44: =SUM(O2:O43) -> 3 | P44: =SUM(P2:P43) -> 21 | Q44: =SUM(Q2:Q43) -> 1 | R44: =SUM(R2:R43) -> 17 | S44: =SUM(O44:R44) -> 42 | T44: =SUM(O44:S44) -> 84
A45: Mismatch in triple object: could-live-with-them != law school | D45: 1 | G45: Mismatch in triple predicate: favorite != is | L45: 1 | O45: =SUM(O44/$T$44) -> 0.035714286 | P45: =SUM(P44/$T$44) -> 0.25 | Q45: =SUM(Q44/$T$44) -> 0.011904762 | R45: =SUM(R44/$T$44) -> 0.20238095 | S45: =SUM(S44/$T$44) -> 0.5
A46: Mismatch in triple object: country-music != country music | C46: 1 | G46: Mismatch in triple predicate: favorite-homemade-meal != is | L46: 1
A47: Mismatch in triple object: couple-days-in-new-york != speaker1 's cameras | D47: 1 | G47: Mismatch in triple predicate: favorite-pizza-toppings != is | I47: 1
A48: Mismatch in triple object: day-going != chicago | D48: 1 | G48: Mismatch in triple predicate: favorite-team != is | H48: 1
A49: Mismatch in triple object: dogs != a cat named mittens | D49: 1 | G49: Mismatch in triple predicate: feed != have | H49: 1
A50: Mismatch in triple object: dyed-blonde != travel | D50: 1 | G50: Mismatch in triple predicate: go != going to | I50: 1
A51: Mismatch in triple object: eggnog != a few christmas gifts | D51: 1 | G51: Mismatch in triple predicate: go-outdoors-and-hike != going | I51: 1
A52: Mismatch in triple object: fair != 88267894 extension to 208 | D52: 1 | G52: Mismatch in triple predicate: go-to != is | I52: 1
A53: Mismatch in triple object: family != fiction | D53: 1 | G53: Mismatch in triple predicate: go-vegan != are from | I53: 1
A54: Mismatch in triple object: farm != horses | E54: 1 | G54: Mismatch in triple predicate: greetings != are | I54: 1
A55: Mismatch in triple object: favorite-red-dress != a bacon enthusiast and appreciation event | D55: 1 | G55: Mismatch in triple predicate: hate != is | I55: 1
A56: Mismatch in triple object: fiction-and-biographies != fiction | E56: 1 | G56: Mismatch in triple predicate: have != like to do for | I56: 1
A57: Mismatch in triple object: fire-in-forest != anything | D57: 1 | G57: Mismatch in triple predicate: have-estimate != is | I57: 1
A58: Mismatch in triple object: fish != a piranha | E58: 1 | G58: Mismatch in triple predicate: have-favorite-movie != is | I58: 1
A59: Mismatch in triple object: fish-i-catch != eat the fish speaker1 catch | E59: 1 | G59: Mismatch in triple predicate: have-hair-color != do | I59: 1
A60: Mismatch in triple object: football-country-music != the colts | D60: 1 | G60: Mismatch in triple predicate: have-hair-color != is | I60: 1
A61: Mismatch in triple object: friends-there-visit != speaker1 's cameras | D61: 1 | G61: Mismatch in triple predicate: have-job != are from | I61: 1
A62: Mismatch in triple object: gig != rock | D62: 1 | G62: Mismatch in triple predicate: have-pet != have | H62: 1
A63: Mismatch in triple object: go-exploring-trip != indian mountains | D63: 1 | G63: Mismatch in triple predicate: have-weakness-for != do for fun | I63: 1
A64: Mismatch in triple object: go-out != a bitcoin company | D64: 1 | G64: Mismatch in triple predicate: help != doing | I64: 1
A65: Mismatch in triple object: going-out-fishing != going out fishing | C65: 1 | G65: Mismatch in triple predicate: hope-to-be != practicing | I65: 1
A66: Mismatch in triple object: gold-medal-1992 != the 100 meter dash | D66: 1 | G66: Mismatch in triple predicate: know != play | I66: 1
A67: Mismatch in triple object: good != binge watching supernatural | D67: 1 | G67: Mismatch in triple predicate: know != say | I67: 1
A68: Mismatch in triple object: good != pastas | D68: 1 | G68: Mismatch in triple predicate: last-learned-about != learn about | J68: 1
A69: Mismatch in triple object: good != tending speaker2 's bars | D69: 1 | G69: Mismatch in triple predicate: laugh != exploring | I69: 1
A70: Mismatch in triple object: guangzhou != the south of china | E70: 1 | G70: Mismatch in triple predicate: learn != learn about | H70: 1
A71: Mismatch in triple object: hats != collect hats | E71: 1 | G71: Mismatch in triple predicate: like != am | I71: 1
A72: Mismatch in triple object: hello != school in florida | D72: 1 | G72: Mismatch in triple predicate: like != docked at | I72: 1
A73: Mismatch in triple object: here != kinda hurting | D73: 1 | G73: Mismatch in triple predicate: like != love | J73: 1
A74: Mismatch in triple object: high-school-japanese != high school japanese | C74: 1 | G74: Mismatch in triple predicate: like != read | I74: 1
A75: Mismatch in triple object: high-school-japanese-and-classes-for-drawing != high school japanese | E75: 1 | G75: Mismatch in triple predicate: like-to-eat != are from | I75: 1
A76: Mismatch in triple object: higher-after-become-permanent-employee != 2500 yuan a month | D76: 1 | G76: Mismatch in triple predicate: like-to-eat != like to | K76: 1
A77: Mismatch in triple object: hobbies != music | E77: 1 | G77: Mismatch in triple predicate: like-to-go != like to | K77: 1
A78: Mismatch in triple object: hobbies != tending speaker2 's bars | D78: 1 | G78: Mismatch in triple predicate: like-to-look-at != like to | K78: 1
A79: Mismatch in triple object: home != the cinema | D79: 1 | G79: Mismatch in triple predicate: like-to-play != play | K79: 1
A80: Mismatch in triple object: home != working from home | E80: 1 | G80: Mismatch in triple predicate: like-to-swim != play | K80: 1
A81: Mismatch in triple object: hs-teacher != pink | D81: 1 | G81: Mismatch in triple predicate: live-with != practicing | I81: 1
A82: Mismatch in triple object: important != melbourne zoo | D82: 1 | G82: Mismatch in triple predicate: look != want to | I82: 1
A83: Mismatch in triple object: indian-mountains-valleys-culture != indian mountains | E83: 1 | G83: Mismatch in triple predicate: love != do | I83: 1
A84: Mismatch in triple object: it != school | D84: 1 | G84: Mismatch in triple predicate: love != do for fun | J84: 1
A85: Mismatch in triple object: it != speaker2 's hobbies | D85: 1 | G85: Mismatch in triple predicate: love != play | I85: 1
A86: Mismatch in triple object: job != teach economics | D86: 1 | G86: Mismatch in triple predicate: love != want to | J86: 1
A87: Mismatch in triple object: kebabs-roast-squid != have kebabs | E87: 1 | G87: Mismatch in triple predicate: love != work with | I87: 1
A88: Mismatch in triple object: kids != 2 of speaker1 's own | D88: 1 | G88: Mismatch in triple predicate: need != exploring | M88: 1
A89: Mismatch in triple object: lake-erie != the canadian army | D89: 1 | G89: Mismatch in triple predicate: need != like to | M89: 1
A90: Mismatch in triple object: latest-episode-face-off != special effects competition | D90: 1 | G90: Mismatch in triple predicate: not-like != like | M90: 1
A91: Mismatch in triple object: little-brother-gods-of-war != violin | D91: 1 | G91: Mismatch in triple predicate: not-like != like to do | M91: 1
A92: Mismatch in triple object: locks-of-love != spiders | D92: 1 | G92: Mismatch in triple predicate: not-mind != are | M92: 1
A93: Mismatch in triple object: lot != history | D93: 1 | G93: Mismatch in triple predicate: not-ride != like to | M93: 1
A94: Mismatch in triple object: meeting-person != english | D94: 1 | G94: Mismatch in triple predicate: not-think != do | M94: 1
A95: Mismatch in triple object: mexican-food != collect hats | D95: 1 | G95: Mismatch in triple predicate: not-understand != like to | M95: 1
A96: Mismatch in triple object: miss-congeniality != miss congeniality | C96: 1 | G96: Mismatch in triple predicate: pay != is | I96: 1
A97: Mismatch in triple object: mother != violin | D97: 1 | G97: Mismatch in triple predicate: play-game != practicing | I97: 1
A98: Mismatch in triple object: movie != fifty shades darker | D98: 1 | G98: Mismatch in triple predicate: play-in != play | H98: 1
A99: Mismatch in triple object: movie != horror movies | E99: 1 | G99: Mismatch in triple predicate: practice != practicing | H99: 1
A100: Mismatch in triple object: movies != horror movies | E100: 1 | G100: Mismatch in triple predicate: put-up-for-rent != like to | I100: 1
...

Sheet convBERT
B1: normalization | C1: different | D1: related | E1: posessive | G1: normalization | H1: different | I1: related | J1: complement | K1: aux | L1: negattion | M1: other | O1: normalization | P1: different | Q1: related | R1: posessive | S1: coref
A2: Mismatch in triple object: '-songshuguiyu-' != speaker2 's order | C2: 1 | F2: Mismatch in triple predicate: ' != can | M2: 1 | N2: Mismatch in triple subject: ' != speaker1 's mom
A3: Mismatch in triple object: 14-yuan != 14 yuan | B3: 1 | F3: Mismatch in triple predicate: ' != did | M3: 1 | N3: Mismatch in triple subject: football != speaker1 | P3: 1
A4: Mismatch in triple object: 1400rmb != about three hours | C4: 1 | F4: Mismatch in triple predicate: ' != is | M4: 1 | N4: Mismatch in triple subject: he != elvin | S4: 1
A5: Mismatch in triple object: 1446-pine != san francisco | C5: 1 | F5: Mismatch in triple predicate: ' != is on | M5: 1 | N5: Mismatch in triple subject: he != justin | S5: 1
A6: Mismatch in triple object: 1446-pine-street != san francisco | C6: 1 | F6: Mismatch in triple predicate: '-s != am | M6: 1 | N6: Mismatch in triple subject: he != rocky | S6: 1
A7: Mismatch in triple object: 2-of-speaker1-'-s-own != 2 of speaker1 's own | B7: 1 | F7: Mismatch in triple predicate: '-s != are | M7: 1 | N7: Mismatch in triple subject: he != sam | S7: 1
A8: Mismatch in triple object: 20310 != 545 8897 | C8: 1 | F8: Mismatch in triple predicate: '-s != arrived | M8: 1 | N8: Mismatch in triple subject: he != speaker1 | S8: 1
A9: Mismatch in triple object: 25 != the paperback | C9: 1 | F9: Mismatch in triple predicate: '-s != been to | M9: 1 | N9: Mismatch in triple subject: he != speaker1 's daughter | S9: 1
A10: Mismatch in triple object: 25-00-dollars-a-week != visitors | C10: 1 | F10: Mismatch in triple predicate: '-s != can | M10: 1 | N10: Mismatch in triple subject: he != speaker1 's ex | S10: 1
A11: Mismatch in triple object: 3-thumbs != lots of stuff | C11: 1 | F11: Mismatch in triple predicate: '-s != can do | M11: 1 | N11: Mismatch in triple subject: he != speaker1 's favorite disney character | S11: 1
A12: Mismatch in triple object: 3000-rib-per-month != 3000 rib per month | B12: 1 | F12: Mismatch in triple predicate: '-s != can let go for | M12: 1 | N12: Mismatch in triple subject: he != speaker1 's husband | S12: 1
A13: Mismatch in triple object: 5-years-now != it field | C13: 1 | F13: Mismatch in triple predicate: '-s != do | M13: 1 | N13: Mismatch in triple subject: he != speaker1 's pug | S13: 1
A14: Mismatch in triple object: 545-8897 != 545 8897 | B14: 1 | F14: Mismatch in triple predicate: '-s != have | M14: 1 | N14: Mismatch in triple subject: he != speaker2 | S14: 1
A15: Mismatch in triple object: 900-yuan != 900 yuan | B15: 1 | F15: Mismatch in triple predicate: '-s != is | M15: 1 | N15: Mismatch in triple subject: he != speaker2 's cat | S15: 1
A16: Mismatch in triple object: 900-yuan != that | C16: 1 | F16: Mismatch in triple predicate: '-s != is in | M16: 1 | N16: Mismatch in triple subject: her-hair != she | R16: 1
A17: Mismatch in triple object: a != a bitcoin company | C17: 1 | F17: Mismatch in triple predicate: '-s != teach | M17: 1 | N17: Mismatch in triple subject: it != 1446 pine street | S17: 1
A18: Mismatch in triple object: a != a librarian | C18: 1 | F18: Mismatch in triple predicate: '-s != was | M18: 1 | N18: Mismatch in triple subject: it != 80 yuan | S18: 1
A19: Mismatch in triple object: a-army-brat != kinda hurting | C19: 1 | F19: Mismatch in triple predicate: '-s != will be | M19: 1 | N19: Mismatch in triple subject: it != a gift for speaker1 's friend | S19: 1
A20: Mismatch in triple object: a-bad-headache != a fever | D20: 1 | F20: Mismatch in triple predicate: '-s-around != is around | M20: 1 | N20: Mismatch in triple subject: it != an arranged marriage | S20: 1
A21: Mismatch in triple object: a-beach-rave != speaker1 's major | C21: 1 | F21: Mismatch in triple predicate: '-s-in != is | G21: 1 | N21: Mismatch in triple subject: it != perkins | S21: 1
A22: Mismatch in triple object: a-big-family != four siblings | D22: 1 | F22: Mismatch in triple predicate: '-s-in != is in | G22: 1 | N22: Mismatch in triple subject: it != speaker1 | P22: 1
A23: Mismatch in triple object: a-bike != how speaker1 get around | C23: 1 | F23: Mismatch in triple predicate: '-s-not != is | N23: Mismatch in triple subject: it != speaker1 's car | S23: 1
A24: Mismatch in triple object: a-birthday-gift != a wedding gift | D24: 1 | F24: Mismatch in triple predicate: agree != accept | I24: 1 | N24: Mismatch in triple subject: it != speaker1 's hat | S24: 1
A25: Mismatch in triple object: a-bit != rather expensive | C25: 1 | F25: Mismatch in triple predicate: am-disabled != do | H25: 1 | N25: Mismatch in triple subject: it != speaker1 's major | S25: 1
A26: Mismatch in triple object: a-bouncer != speaker1 's neck | C26: 1 | F26: Mismatch in triple predicate: am-more-of != played | H26: 1 | N26: Mismatch in triple subject: it != speaker1 's new house | S26: 1
A27: Mismatch in triple object: a-boy-or-girl != a female | C27: 1 | F27: Mismatch in triple predicate: am-not != am | L27: 1 | N27: Mismatch in triple subject: it != speaker1 's special recipe | S27: 1
A28: Mismatch in triple object: a-busy-house-'-s-cats != speaker1 's home | C28: 1 | F28: Mismatch in triple predicate: appreciate != have | H28: 1 | N28: Mismatch in triple subject: it != speaker1 's yacht | S28: 1
A29: Mismatch in triple object: a-cat != a pet | D29: 1 | F29: Mismatch in triple predicate: are-all-in != are in | I29: 1 | N29: Mismatch in triple subject: it != speaker2 | P29: 1
A30: Mismatch in triple object: a-cat-named-mittens != a cat named mittens | B30: 1 | F30: Mismatch in triple predicate: are-out != know | H30: 1 | N30: Mismatch in triple subject: it != that | S30: 1
A31: Mismatch in triple object: a-chevy-person != growing up | C31: 1 | F31: Mismatch in triple predicate: aux != can | K31: 1 | N31: Mismatch in triple subject: it != the fitting room | S31: 1
A32: Mismatch in triple object: a-child != a child | B32: 1 | F32: Mismatch in triple predicate: aux != can do | K32: 1 | N32: Mismatch in triple subject: it != the flight | S32: 1
A33: Mismatch in triple object: a-child-from-a-previous-marriage != a child from a previous marriage | B33: 1 | F33: Mismatch in triple predicate: aux != could be | K33: 1 | N33: Mismatch in triple subject: it != the master bedroom | S33: 1
A34: Mismatch in triple object: a-child-from-a-previous-marriage != one child | D34: 1 | F34: Mismatch in triple predicate: aux != is about | K34: 1 | N34: Mismatch in triple subject: it != the words of the song | S34: 1
A35: Mismatch in triple object: a-chinese-new-year-'-s-gift != a wedding gift | D35: 1 | F35: Mismatch in triple predicate: aux != loves to | K35: 1 | N35: Mismatch in triple subject: it != this party | S35: 1
A36: Mismatch in triple object: a-cold != a cold | B36: 1 | F36: Mismatch in triple predicate: aux != need to | K36: 1 | N36: Mismatch in triple subject: it != this perfume | S36: 1
A37: Mismatch in triple object: a-cold != speaker1 | C37: 1 | F37: Mismatch in triple predicate: aux != will | K37: 1 | N37: Mismatch in triple subject: kevin-'-s-salary != kevin | Q37: 1
A38: Mismatch in triple object: a-comic-book-collection-baking-stuffs != baking stuffs | C38: 1 | F38: Mismatch in triple predicate: be != am | G38: 1 | N38: Mismatch in triple subject: kiddos != there | P38: 1
A39: Mismatch in triple object: a-comp-lit-major != a comp lit major | B39: 1 | F39: Mismatch in triple predicate: be != are | G39: 1 | N39: Mismatch in triple subject: matter != speaker1 | P39: 1
A40: Mismatch in triple object: a-comparative-literature-major != a comp lit major | B40: 1 | F40: Mismatch in triple predicate: be != are from | K40: 1 | N40: Mismatch in triple subject: panda != the kangaroo | P40: 1
A41: Mismatch in triple object: a-concert != a concert | B41: 1 | F41: Mismatch in triple predicate: be != are in | K41: 1 | N41: Mismatch in triple subject: she != speaker1 's husbands mother | S41: 1
A42: Mismatch in triple object: a-construction-worker != a construction worker | B42: 1 | F42: Mismatch in triple predicate: be != are up to | K42: 1 | N42: Mismatch in triple subject: she != speaker1 's wife | S42: 1
A43: Mismatch in triple object: a-couple-of-days != take it easy | C43: 1 | F43: Mismatch in triple predicate: be != been to | K43: 1 | N43: Mismatch in triple subject: shopping != speaker1 's favorite thing | P43: 1
A44: Mismatch in triple object: a-couple-thousand != a couple thousand for the whole set | B44: 1 | F44: Mismatch in triple predicate: be != can | H44: 1 | N44: Mismatch in triple subject: speaker1 != being vegan | P44: 1
A45: Mismatch in triple object: a-cub != a black bear | C45: 1 | F45: Mismatch in triple predicate: be != could leave | H45: 1 | N45: Mismatch in triple subject: speaker1 != guangzhou | P45: 1
A46: Mismatch in triple object: a-diver-'-s-license != a diver 's license | B46: 1 | F46: Mismatch in triple predicate: be != did | H46: 1 | N46: Mismatch in triple subject: speaker1 != outdoor class | P46: 1
A47: Mismatch in triple object: a-doctor != a cold | C47: 1 | F47: Mismatch in triple predicate: be != donate to | H47: 1 | N47: Mismatch in triple subject: speaker1 != she | S47: 1
A48: Mismatch in triple object: a-dog-house-big != a dog house big enough for many dogs | B48: 1 | F48: Mismatch in triple predicate: be != going to be | H48: 1 | N48: Mismatch in triple subject: speaker1 != siblings | P48: 1
A49: Mismatch in triple object: a-dog-trainer != a service | C49: 1 | F49: Mismatch in triple predicate: be != got | H49: 1 | N49: Mismatch in triple subject: speaker1 != speaker1 's english | R49: 1
A50: Mismatch in triple object: a-family != well | C50: 1 | F50: Mismatch in triple predicate: be != hate | H50: 1 | N50: Mismatch in triple subject: speaker1 != speaker1 's friends | R50: 1
A51: Mismatch in triple object: a-favorite-activity != disney | C51: 1 | F51: Mismatch in triple predicate: be != have | H51: 1 | N51: Mismatch in triple subject: speaker1 != speaker1 's sisters | R51: 1
A52: Mismatch in triple object: a-female != make more money | C52: 1 | F52: Mismatch in triple predicate: be != is | G52: 1 | N52: Mismatch in triple subject: speaker1 != speaker2 | R52: 1
A53: Mismatch in triple object: a-fever != a fever | B53: 1 | F53: Mismatch in triple predicate: be != is around | K53: 1 | N53: Mismatch in triple subject: speaker1 != that | P53: 1
A54: Mismatch in triple object: a-few-weeks != win | C54: 1 | F54: Mismatch in triple predicate: be != is on | K54: 1 | N54: Mismatch in triple subject: speaker1 != that show | P54: 1
A55: Mismatch in triple object: a-gold-medal != the 100 meter dash | C55: 1 | F55: Mismatch in triple predicate: be != like | H55: 1 | N55: Mismatch in triple subject: speaker1 != the antidote for the everyday sickness | P55: 1
A56: Mismatch in triple object: a-good-price != the internet | C56: 1 | F56: Mismatch in triple predicate: be != like to | H56: 1 | N56: Mismatch in triple subject: speaker1 != they | S56: 1
A57: Mismatch in triple object: a-guest-book-on-the-website-for-people-to-sign != a guest book on the website | B57: 1 | F57: Mismatch in triple predicate: be != listen to | H57: 1 | N57: Mismatch in triple subject: speaker1 != this | P57: 1
A58: Mismatch in triple object: a-high-fever != a high fever | B58: 1 | F58: Mismatch in triple predicate: be != opened | H58: 1 | N58: Mismatch in triple subject: speaker1 != we | S58: 1
A59: Mismatch in triple object: a-house != a house | B59: 1 | F59: Mismatch in triple predicate: be != paying with | H59: 1 | N59: Mismatch in triple subject: speaker1-' != speaker1 | O59: 1
A60: Mismatch in triple object: a-job != a singer | C60: 1 | F60: Mismatch in triple predicate: be != played | H60: 1 | N60: Mismatch in triple subject: speaker1-' != speaker2 | P60: 1
A61: Mismatch in triple object: a-kid != a kid | B61: 1 | F61: Mismatch in triple predicate: be != saying | H61: 1 | N61: Mismatch in triple subject: speaker1-'-s-best-friend != speaker2 | S61: 1
A62: Mismatch in triple object: a-kid != music | C62: 1 | F62: Mismatch in triple predicate: be != should be | H62: 1 | N62: Mismatch in triple subject: speaker1-'-s-car != it | P62: 1
A63: Mismatch in triple object: a-large-room != book a suite for 4 people | D63: 1 | F63: Mismatch in triple predicate: be != thought about | H63: 1 | N63: Mismatch in triple subject: speaker1-'-s-dad-other-doctors != speaker1 | P63: 1
A64: Mismatch in triple object: a-large-room != book it | C64: 1 | F64: Mismatch in triple predicate: be != walk | H64: 1 | N64: Mismatch in triple subject: speaker1-'-s-dad-other-doctors != speaker1 's dad | O64: 1
A65: Mismatch in triple object: a-larp-or-nah != a larp | B65: 1 | F65: Mismatch in triple predicate: be != was | H65: 1 | N65: Mismatch in triple subject: speaker1-'-s-day != speaker1 | P65: 1
A66: Mismatch in triple object: a-lawyer != a lawyer | B66: 1 | F66: Mismatch in triple predicate: be != will be | H66: 1 | N66: Mismatch in triple subject: speaker1-'-s-english != speaker1 's english | O66: 1
A67: Mismatch in triple object: a-lawyer != dance | C67: 1 | F67: Mismatch in triple predicate: be-around != is | H67: 1 | N67: Mismatch in triple subject: speaker1-'-s-five-sons != speaker1 's five sons | O67: 1
A68: Mismatch in triple object: a-librarian != a librarian | B68: 1 | F68: Mismatch in triple predicate: be-from != are | G68: 1 | N68: Mismatch in triple subject: speaker1-'-s-girlfriend != speaker1 | P68: 1
A69: Mismatch in triple object: a-little-bit-to-be-honest != kinda hurting | D69: 1 | F69: Mismatch in triple predicate: be-from != is | G69: 1 | N69: Mismatch in triple subject: speaker1-'-s-hat != speaker1 's hat | O69: 1
A70: Mismatch in triple object: a-lot != heavy | C70: 1 | F70: Mismatch in triple predicate: be-here-to != seeing | H70: 1 | N70: Mismatch in triple subject: speaker1-'-s-mom != speaker1 | P70: 1
A71: Mismatch in triple object: a-lot-of-fun != going | C71: 1 | F71: Mismatch in triple predicate: be-no != are | H71: 1 | N71: Mismatch in triple subject: speaker1-'-s-mother-in-law != she | S71: 1
A72: Mismatch in triple object: a-lot-of-history != the ring road | C72: 1 | F72: Mismatch in triple predicate: beat-at != play | H72: 1 | N72: Mismatch in triple subject: speaker1-'-s-mother-in-law != speaker1 | P72: 1
A73: Mismatch in triple object: a-lot-of-history != about 200 years old | C73: 1 | F73: Mismatch in triple predicate: been-to-for != did | H73: 1 | N73: Mismatch in triple subject: speaker1-'-s-mother-in-law != speaker1 's mother in law | O73: 1
A74: Mismatch in triple object: a-lot-of-money != round the world | C74: 1 | F74: Mismatch in triple predicate: break != can | H74: 1 | N74: Mismatch in triple subject: speaker1-'-s-pen-name != speaker1 | P74: 1
A75: Mismatch in triple object: a-master-card != sit next to a window | C75: 1 | F75: Mismatch in triple predicate: bring-with != are | H75: 1 | N75: Mismatch in triple subject: speaker1-'-s-uncle != speaker1 's uncle | O75: 1
A76: Mismatch in triple object: a-message-for-him != a message for him | B76: 1 | F76: Mismatch in triple predicate: call != have | H76: 1 | N76: Mismatch in triple subject: speaker1-mother != speaker2 | P76: 1
A77: Mismatch in triple object: a-most-popular-dish != fish steamed | D77: 1 | F77: Mismatch in triple predicate: call-speaker2 != tastes like | H77: 1 | N77: Mismatch in triple subject: speaker2 != ikea | P77: 1
A78: Mismatch in triple object: a-movie != fifty shades darker | C78: 1 | F78: Mismatch in triple predicate: came-out-of != was | H78: 1 | N78: Mismatch in triple subject: speaker2 != it | P78: 1
A79: Mismatch in triple object: a-nice-day != a lot of work in the office | C79: 1 | F79: Mismatch in triple predicate: can-add != able to | K79: 1 | N79: Mismatch in triple subject: speaker2 != perkins | P79: 1
A80: Mismatch in triple object: a-package-that-includes-all-the-movie-channels-with-the-basic-channels != a package that includes all the movie channels | B80: 1 | F80: Mismatch in triple predicate: can-find-on != singing along to | H80: 1 | N80: Mismatch in triple subject: speaker2 != princeton | P80: 1
A81: Mismatch in triple object: a-parenting-book != turn speaker1 's life around | C81: 1 | F81: Mismatch in triple predicate: can-find-speaker1-on != am in | H81: 1 | N81: Mismatch in triple subject: speaker2 != she | P81: 1
A82: Mismatch in triple object: a-pay != small change | C82: 1 | F82: Mismatch in triple predicate: can-find-speaker1-on != can find | K82: 1 | N82: Mismatch in triple subject: speaker2 != speaker1 | P82: 1
A83: Mismatch in triple object: a-pet != a black bear | C83: 1 | F83: Mismatch in triple predicate: can-learn != can learn | G83: 1 | N83: Mismatch in triple subject: speaker2 != speaker1 's father | P83: 1
A84: Mismatch in triple object: a-pet != a pet | B84: 1 | F84: Mismatch in triple predicate: can-learn != need | H84: 1 | N84: Mismatch in triple subject: speaker2 != speaker1 's wife | P84: 1
A85: Mismatch in triple object: a-pet-fish != a pet | D85: 1 | F85: Mismatch in triple predicate: can-put != can put | G85: 1 | N85: Mismatch in triple subject: speaker2 != speaker2 's hobbies | P85: 1
A86: Mismatch in triple object: a-piranha != a piranha | B86: 1 | F86: Mismatch in triple predicate: cancer != am | H86: 1 | N86: Mismatch in triple subject: speaker2 != swimming | P86: 1
A87: Mismatch in triple object: a-previous-relationship != a child from a previous marriage | D87: 1 | F87: Mismatch in triple predicate: catch != like to | H87: 1 | N87: Mismatch in triple subject: speaker2 != that | P87: 1
A88: Mismatch in triple object: a-previous-relationship != one child | D88: 1 | F88: Mismatch in triple predicate: change != can have | H88: 1 | N88: Mismatch in triple subject: speaker2 != the cigarettes | P88: 1
A89: Mismatch in triple object: a-rail-road != much | C89: 1 | F89: Mismatch in triple predicate: change != have | H89: 1 | N89: Mismatch in triple subject: speaker2 != the reservation | P89: 1
A90: Mismatch in triple object: a-reservation != a reservation | B90: 1 | F90: Mismatch in triple predicate: charge-for != charge for | G90: 1 | N90: Mismatch in triple subject: speaker2 != these | P90: 1
A91: Mismatch in triple object: a-reservation-in-shanghai != a reservation | D91: 1 | F91: Mismatch in triple predicate: close != have | H91: 1 | N91: Mismatch in triple subject: speaker2 != they | P91: 1
A92: Mismatch in triple object: a-restaurant != a restaurant | B92: 1 | F92: Mismatch in triple predicate: close-with != close with | G92: 1 | N92: Mismatch in triple subject: speaker2 != this | P92: 1
A93: Mismatch in triple object: a-service-charge != 900 yuan | C93: 1 | F93: Mismatch in triple predicate: come != coming to | G93: 1 | N93: Mismatch in triple subject: speaker2-'-s != speaker1 's plans | P93: 1
A94: Mismatch in triple object: a-service-charge != that | C94: 1 | F94: Mismatch in triple predicate: come-back-from != visit | H94: 1 | N94: Mismatch in triple subject: speaker2-'-s-biggest-fear != speaker1 | P94: 1
A95: Mismatch in triple object: a-teller-in-a-bank != night school | C95: 1 | F95: Mismatch in triple predicate: come-back-in != want you to | H95: 1 | N95: Mismatch in triple subject: speaker2-'-s-biggest-fear != speaker1 's biggest fear | P95: 1
A96: Mismatch in triple object: a-transfer != the office | C96: 1 | F96: Mismatch in triple predicate: commerce-transaction != exceed | H96: 1 | N96: Mismatch in triple subject: speaker2-'-s-dogs-name != speaker1 | P96: 1
A97: Mismatch in triple object: a-vegan-hard != hard | C97: 1 | F97: Mismatch in triple predicate: commerce-transaction != pay for | I97: 1 | N97: Mismatch in triple subject: speaker2-'-s-favorite-disney-character != speaker1 's favorite disney character | O97: 1
A98: Mismatch in triple object: a-vegan-hard != music | C98: 1 | F98: Mismatch in triple predicate: commerce-transaction != was for | H98: 1 | N98: Mismatch in triple subject: speaker2-'-s-favorite-food != speaker1 's favorite food | O98: 1
A99: Mismatch in triple object: a-very-interesting-job != speaker2 's hobby | C99: 1 | F99: Mismatch in triple predicate: cook != like to | H99: 1 | N99: Mismatch in triple subject: speaker2-'-s-favorite-holiday != speaker1 's favorite holiday | P99: 1
A100: Mismatch in triple object: a-video-camera != anything to declare | C100: 1 | F100: Mismatch in triple predicate: cook-together-at != cook together at | G100: 1 | N100: Mismatch in triple subject: speaker2-'-s-favorite-movie != speaker1 's favorite movie | P100: 1
...

Sheet Blad3
A1: element | B1: model | C1: normalization | D1: different | E1: related | F1: posessive | G1: coref | H1: aux | I1: negattion | J1: other
A2: subject | B2: convBERT | C2: =convBERT!O127 -> 0.10569106 | D2: =convBERT!P127 -> 0.52845528 | E2: =convBERT!Q127 -> 0.016260163 | F2: =convBERT!R127 -> 0.040650407 | G2: =convBERT!S127 -> 0.30894309 | H2: n.a. | I2: n.a. | J2: n.a.
B3: Qwen2.5 | C3: ='Errors Qwen2.5'!O45 -> 0.035714286 | D3: ='Errors Qwen2.5'!P45 -> 0.25 | E3: ='Errors Qwen2.5'!Q45 -> 0.011904762 | F3: ='Errors Qwen2.5'!R45 -> 0.20238095 | G3: ='Errors Qwen2.5'!S45 -> 0.5 | H3: n.a. | I3: n.a. | J3: n.a.
A4: object | B4: convBERT | C4: =convBERT!B555 -> 0.20871143 | D4: =convBERT!C555 -> 0.63883848 | E4: =convBERT!D555 -> 0.13793103 | F4: =convBERT!E555 -> 0.014519056 | G4: 0 | H4: n.a. | I4: n.a. | J4: n.a.
B5: Qwen2.5 | C5: ='Errors Qwen2.5'!C153 -> 0.10666667 | D5: ='Errors Qwen2.5'!D153 -> 0.68 | E5: ='Errors Qwen2.5'!E153 -> 0.17333333 | F5: ='Errors Qwen2.5'!F153 -> 0 | G5: 0 | H5: n.a. | I5: n.a. | J5: n.a.
A6: predicate | B6: convBERT | C6: =convBERT!G375 -> 0.14285714 | D6: =convBERT!H375 -> 0.66846361 | E6: =convBERT!I375 -> 0.078167116 | F6: n.a. | G6: n.a. | H6: =convBERT!K375 -> 0.053908356 | I6: =convBERT!L375 -> 0.0053908356 | J6: =convBERT!M375 -> 0.051212938
B7: Qwen2.5 | C7: ='Errors Qwen2.5'!H130 -> 0.13559322 | D7: ='Errors Qwen2.5'!I130 -> 0.59322034 | E7: ='Errors Qwen2.5'!J130 -> 0.050847458 | F7: n.a. | G7: n.a. | H7: ='Errors Qwen2.5'!K130 -> 0.042372881 | I7: ='Errors Qwen2.5'!L130 -> 0.10169492 | J7: ='Errors Qwen2.5'!M130 -> 0.076271186
